exactcis/__init__.py
exactcis/_version.py
exactcis/cli.py
exactcis/core.py
exactcis/methods/__init__.py
exactcis/methods/blaker.py
exactcis/methods/conditional.py
exactcis/methods/midp.py
exactcis/methods/unconditional.py
exactcis/methods/wald.py
exactcis/utils/__init__.py
exactcis/utils/calculators.py
exactcis/utils/data_models.py
exactcis/utils/optimization.py
exactcis/utils/parallel.py
exactcis/utils/pmf_functions.py
exactcis/utils/root_finding.py
exactcis/utils/stats.py
exactcis/utils/transformers.py
exactcis/utils/validators.py
exactcis-0.1.0.dist-info/METADATA
exactcis-0.1.0.dist-info/WHEEL
exactcis-0.1.0.dist-info/entry_points.txt
exactcis-0.1.0.dist-info/licenses/LICENSE
exactcis-0.1.0.dist-info/RECORD
