Metadata-Version: 2.4
Name: exactcis
Version: 0.1.0
Summary: Exact confidence intervals for odds ratios
Project-URL: Homepage, https://github.com/exactcis/exactcis
Project-URL: Bug Tracker, https://github.com/exactcis/exactcis/issues
Project-URL: Documentation, https://github.com/exactcis/exactcis/docs
Author-email: ExactCIs Contributors <exactcis-dev@example.org>
License: MIT
License-File: LICENSE
Classifier: Intended Audience :: Science/Research
Classifier: License :: OSI Approved :: MIT License
Classifier: Operating System :: OS Independent
Classifier: Programming Language :: Python :: 3
Classifier: Topic :: Scientific/Engineering :: Information Analysis
Classifier: Topic :: Scientific/Engineering :: Mathematics
Classifier: Topic :: Scientific/Engineering :: Medical Science Apps.
Classifier: Topic :: Software Development :: Libraries :: Python Modules
Requires-Python: >=3.9
Requires-Dist: numpy<2.0,>=1.21
Requires-Dist: scipy>=1.12.0
Requires-Dist: statsmodels>=0.14.0
Requires-Dist: typing-extensions; python_version < '3.10'
Provides-Extra: dev
Requires-Dist: black>=23.0.0; extra == 'dev'
Requires-Dist: line-profiler>=5.0.0; extra == 'dev'
Requires-Dist: memory-profiler>=0.61.0; extra == 'dev'
Requires-Dist: mypy>=1.0.0; extra == 'dev'
Requires-Dist: pre-commit>=3.0.0; extra == 'dev'
Requires-Dist: psutil>=7.0.0; extra == 'dev'
Requires-Dist: pytest-cov>=4.1.0; extra == 'dev'
Requires-Dist: pytest-timeout>=2.1.0; extra == 'dev'
Requires-Dist: pytest-xdist>=3.3.1; extra == 'dev'
Requires-Dist: pytest>=8.3.5; extra == 'dev'
Requires-Dist: ruff>=0.0.270; extra == 'dev'
Requires-Dist: tqdm>=4.65.0; extra == 'dev'
Provides-Extra: full
Requires-Dist: matplotlib>=3.4.0; extra == 'full'
Requires-Dist: pandas>=1.3.0; extra == 'full'
Requires-Dist: sympy>=1.9.0; extra == 'full'
Requires-Dist: tqdm>=4.62.0; extra == 'full'
Provides-Extra: pandas
Requires-Dist: pandas>=1.3.0; extra == 'pandas'
Provides-Extra: sympy
Requires-Dist: sympy>=1.9.0; extra == 'sympy'
Provides-Extra: tqdm
Requires-Dist: tqdm>=4.62.0; extra == 'tqdm'
Provides-Extra: viz
Requires-Dist: matplotlib>=3.4.0; extra == 'viz'
